LICENSE
MANIFEST.in
README.md
pyproject.toml
src/luau/__init__.py
src/luau/convert.py
src/luau/path.py
src/luau.egg-info/PKG-INFO
src/luau.egg-info/SOURCES.txt
src/luau.egg-info/dependency_links.txt
src/luau.egg-info/requires.txt
src/luau.egg-info/top_level.txt
src/luau/data/py_luau_rojo.exe
src/luau/data/py_luau_stylua.exe
src/luau/data/py_luau_wpt.exe
src/luau/roblox/__init__.py
src/luau/roblox/api.py
src/luau/roblox/rojo.py
src/luau/roblox/util.py