Metadata-Version: 2.1
Name: luau
Version: 0.4.19
Summary: a basic python package for writing luau scripts
Author-email: nightcycle <coyer@nightcycle.us>
Classifier: Programming Language :: Python :: 3
Classifier: Operating System :: OS Independent
Requires-Python: >=3.10
License-File: LICENSE
